[
  {
    "id": 1,
    "name": "Nguyễn Văn Ba",
    "username": "BaNV",
    "email": "nva@gmail.com",
    "phone": "3334445556",
    "type": "Admin"
  },
  {
    "id": 2,
    "name": "Trần Văn Bảy",
    "username": "BayTV",
    "email": "tvb@gmail.com",
    "phone": "2223335556",
    "type": "User"
  },
  {
    "id": 3,
    "name": "Vũ Thị Hồng",
    "username": "HongVT",
    "email": "vth@gmail.com",
    "phone": "1112223334",
    "type": "User"
  },
  {
    "id": 4,
    "name": "Lê Thị Năm",
    "username": "NamLT",
    "email": "ltn@gmail.com",
    "phone": "6667779933",
    "type": "User"
  }
]